{"DocumentConnection":{"type":"DocumentConnection","resolveType":"multiCollectionDocumentList","collections":["blogs_posts"]},"Node":{"type":"Node","resolveType":"nodeDocument"},"DocumentNode":{"type":"DocumentNode","resolveType":"multiCollectionDocument","createDocument":"create","updateDocument":"update"},"Blogs_posts":{"type":"Blogs_posts","resolveType":"collectionDocument","collection":"blogs_posts","createBlogs_posts":"create","updateBlogs_posts":"update"},"Blogs_postsConnection":{"type":"Blogs_postsConnection","resolveType":"collectionDocumentList","collection":"blogs_posts"}}